aiocqlengine/__init__.py
aiocqlengine/models.py
aiocqlengine/query.py
aiocqlengine/session.py
aiocqlengine-0.3.2.dist-info/LICENSE
aiocqlengine-0.3.2.dist-info/WHEEL
aiocqlengine-0.3.2.dist-info/METADATA
aiocqlengine-0.3.2.dist-info/RECORD
