Metadata-Version: 2.1
Name: aiocqlengine
Version: 0.3.2
Summary: Async wrapper for cqlengine of cassandra python driver.
License: MIT
Author: Darren
Author-email: charact3@gmail.com
Requires-Python: >=3.6,<4.0
Classifier: License :: OSI Approved :: MIT License
Classifier: Programming Language :: Python :: 3
Classifier: Programming Language :: Python :: 3.6
Classifier: Programming Language :: Python :: 3.7
Classifier: Programming Language :: Python :: 3.8
Classifier: Programming Language :: Python :: 3.9
Requires-Dist: cassandra-driver (>=3.20,<4.0)
